uv_mcp/__init__.py
uv_mcp/cli.py
uv_mcp/server.py
uv_mcp/uv_wrapper.py
uv_mcp-0.3.0.dist-info/METADATA
uv_mcp-0.3.0.dist-info/WHEEL
uv_mcp-0.3.0.dist-info/entry_points.txt
uv_mcp-0.3.0.dist-info/RECORD
