Metadata-Version: 2.4
Name: uv-mcp
Version: 0.3.0
Summary: Model Context Protocol (MCP) server for interacting with Python installations via uv
Project-URL: Homepage, https://github.com/dmclain/uv-mcp
Project-URL: Bug Tracker, https://github.com/dmclain/uv-mcp/issues
Author-email: uv-mcp Contributors <dmclain@gmail.com>
License: MIT
Classifier: License :: OSI Approved :: MIT License
Classifier: Operating System :: OS Independent
Classifier: Programming Language :: Python :: 3
Requires-Python: >=3.10
Requires-Dist: mcp>=1.5.0
Requires-Dist: uv>=0.6.9
Provides-Extra: dev
Requires-Dist: mypy; extra == 'dev'
Requires-Dist: pytest; extra == 'dev'
